timewalk/__init__.py
timewalk/backtest.py
timewalk/feature_builder.py
timewalk/strategy_classes.py
timewalk/yf_helper.py
timewalk-0.0.1.dist-info/LICENSE
timewalk-0.0.1.dist-info/METADATA
timewalk-0.0.1.dist-info/WHEEL
timewalk-0.0.1.dist-info/top_level.txt
timewalk-0.0.1.dist-info/RECORD
