Metadata-Version: 2.2
Name: timewalk
Version: 0.0.1
Summary: A simple backtesting library for market strategies
Author-email: Deni Rakovic <deni.rakovic23@gmail.com>
License: MIT License
Project-URL: Homepage, https://github.com/drakovic23/timewalk
Project-URL: Issues, https://github.com/drakovic23/timewalk/issues
Classifier: Programming Language :: Python :: 3
Classifier: Operating System :: OS Independent
Requires-Python: >=3.8
License-File: LICENSE
Requires-Dist: pandas>=2.2.3
Requires-Dist: numpy>=2.0.0
Requires-Dist: yfinance>=0.2.52
Requires-Dist: numba>=0.60.0
Provides-Extra: dev
Requires-Dist: pytest>=8.3.4; extra == "dev"
